MANIFEST.in
readme.md
requirements.txt
setup.py
sms_utilities/SMS_Deliver.py
sms_utilities/SMS_Helper.py
sms_utilities/SMS_Parse.py
sms_utilities/SMS_Submit.py
sms_utilities/__init__.py
sms_utilities/rpdu.py
sms_utilities.egg-info/PKG-INFO
sms_utilities.egg-info/SOURCES.txt
sms_utilities.egg-info/dependency_links.txt
sms_utilities.egg-info/not-zip-safe
sms_utilities.egg-info/pbr.json
sms_utilities.egg-info/requires.txt
sms_utilities.egg-info/top_level.txt