Metadata-Version: 1.1
Name: sms-utilities
Version: 0.0.2
Summary: SMS encoding and decoding utilities
Home-page: https://github.com/endaga/sms_utilities
Author: Matt Ball
Author-email: matt@endaga.com
License: MIT
Download-URL: https://github.com/endaga/sms_utilities/0.0.2
Platform: UNKNOWN
